pyzbar/__init__.py
pyzbar/locations.py
pyzbar/pyzbar.py
pyzbar/pyzbar_error.py
pyzbar/wrapper.py
pyzbar/zbar_library.py
pyzbar/tests/__init__.py
pyzbar/tests/code128.png
pyzbar/tests/empty.png
pyzbar/tests/qrcode.png
pyzbar/tests/qrcode_rotated.png
pyzbar/tests/test_locations.py
pyzbar/tests/test_pyzbar.py
pyzbar/tests/test_zbar_library.py
pyzbar_x-0.2.1.dist-info/LICENSE.txt
pyzbar_x-0.2.1.dist-info/METADATA
pyzbar_x-0.2.1.dist-info/WHEEL
pyzbar_x-0.2.1.dist-info/top_level.txt
pyzbar_x-0.2.1.dist-info/RECORD
