Metadata-Version: 2.1
Name: pyzbar-x
Version: 0.2.1
Summary: Read one-dimensional barcodes and QR codes from Python 3.
Home-page: https://github.com/dferens/pyzbar/
Author: Lawrence Hudson
Author-email: quicklizard@googlemail.com
License: MIT
Platform: UNKNOWN
Classifier: Development Status :: 4 - Beta
Classifier: License :: OSI Approved :: MIT License
Classifier: Topic :: Utilities
Classifier: Programming Language :: Python :: 3
Classifier: Programming Language :: Python :: 3.5
Classifier: Programming Language :: Python :: 3.6
Classifier: Programming Language :: Python :: 3.7
Classifier: Programming Language :: Python :: 3.8
Classifier: Programming Language :: Python :: 3.9
